dushibian_strapi_client/__init__.py
dushibian_strapi_client/api/__init__.py
dushibian_strapi_client/api/activity_api.py
dushibian_strapi_client/api/article_api.py
dushibian_strapi_client/api/book_api.py
dushibian_strapi_client/api/home_api.py
dushibian_strapi_client/api/person_api.py
dushibian_strapi_client/api/recommend_api.py
dushibian_strapi_client/api/siteconfig_api.py
dushibian_strapi_client/api/tag_api.py
dushibian_strapi_client/api/upload_file_api.py
dushibian_strapi_client/api/users_permissions_auth_api.py
dushibian_strapi_client/api/users_permissions_users_roles_api.py
dushibian_strapi_client/api_client.py
dushibian_strapi_client/api_response.py
dushibian_strapi_client/configuration.py
dushibian_strapi_client/exceptions.py
dushibian_strapi_client/models/__init__.py
dushibian_strapi_client/models/activity.py
dushibian_strapi_client/models/activity_created_by.py
dushibian_strapi_client/models/activity_created_by_data.py
dushibian_strapi_client/models/activity_list_response.py
dushibian_strapi_client/models/activity_list_response_data_item.py
dushibian_strapi_client/models/activity_list_response_meta.py
dushibian_strapi_client/models/activity_list_response_meta_pagination.py
dushibian_strapi_client/models/activity_request.py
dushibian_strapi_client/models/activity_request_data.py
dushibian_strapi_client/models/activity_response.py
dushibian_strapi_client/models/activity_response_data_object.py
dushibian_strapi_client/models/article.py
dushibian_strapi_client/models/article_list_response.py
dushibian_strapi_client/models/article_list_response_data_item.py
dushibian_strapi_client/models/article_request.py
dushibian_strapi_client/models/article_request_data.py
dushibian_strapi_client/models/article_request_data_tags_inner.py
dushibian_strapi_client/models/article_response.py
dushibian_strapi_client/models/article_response_data_object.py
dushibian_strapi_client/models/article_tags.py
dushibian_strapi_client/models/article_tags_data_inner.py
dushibian_strapi_client-1.0.0.dist-info/METADATA
dushibian_strapi_client-1.0.0.dist-info/WHEEL
dushibian_strapi_client-1.0.0.dist-info/RECORD
